notebook_mapper/__init__.py
notebook_mapper/__version__
notebook_mapper/automapper_template.py
notebook_mapper/utils.py
notebook_mapper-0.0.14.dist-info/DESCRIPTION.rst
notebook_mapper-0.0.14.dist-info/METADATA
notebook_mapper-0.0.14.dist-info/RECORD
notebook_mapper-0.0.14.dist-info/WHEEL
notebook_mapper-0.0.14.dist-info/metadata.json
notebook_mapper-0.0.14.dist-info/top_level.txt
