Metadata-Version: 2.0
Name: notebook-mapper
Version: 0.0.14
Summary: Jupyter Notebooks + Windows Server mapped drives toolkit.
Home-page: https://github.com/draperjames/notebook_mapper
Author: James Draper
Author-email: james.draper@duke.edu
License: MIT
Keywords: jupyter,notebook,Windows,Mapped Drive,Windows Server
Platform: POSIX
Platform: Windows
Classifier: Development Status :: 5 - Production/Stable
Classifier: License :: OSI Approved :: MIT License
Classifier: Operating System :: Microsoft :: Windows
Classifier: Operating System :: POSIX
Classifier: Programming Language :: Python :: 3.5
Classifier: Programming Language :: Python :: 3.6
Classifier: Programming Language :: Python :: 3.7
Classifier: Topic :: Software Development :: Build Tools
Classifier: Topic :: System :: Systems Administration
Provides: notebook_mapper
